[
    {
        "title": "Trop de patients ont \u00e9t\u00e9 d\u00e9clar\u00e9s aptes au travail",
        "summary": "PMEDA, l\u2019entreprise qui effectuait des expertises m\u00e9dicales pour l\u2019AI, a refus\u00e9 nettement plus de rentes AI que l\u2019ensemble de ses concurrents. Berne ne travaillera plus avec elle, rapporte la \u00abSonntagsZeitung\u00bb.",
        "link": "https://www.20min.ch/fr/136221151830"
    },
    {
        "title": "Un couple a confi\u00e9 des liasses de billets \u00e0 un soi-disant coursier",
        "summary": "Un homme a \u00e9t\u00e9 arr\u00eat\u00e9 vendredi apr\u00e8s avoir collect\u00e9 \u00e0 plusieurs reprises d\u2019importantes sommes d\u2019argent aupr\u00e8s d\u2019un couple de Zurichois.",
        "link": "https://www.20min.ch/fr/962186455081"
    },
    {
        "title": "L\u2019afflux de r\u00e9fugi\u00e9s conduit \u00e0 la p\u00e9nurie de conteneurs",
        "summary": "En un an, 2500 \u00e0 3000 conteneurs d\u2019habitation ont \u00e9t\u00e9 construits pour loger les r\u00e9fugi\u00e9s dans le pays. Les fabricants peinent \u00e0 faire face \u00e0 la demande, notamment des \u00e9coles. Des communes en appellent \u00e0 Berne.",
        "link": "https://www.20min.ch/fr/262058782815"
    },
    {
        "title": "Mort de 5 b\u00e9b\u00e9s pr\u00e9matur\u00e9s et de 7 patients \u00e0 l\u2019h\u00f4pital al-Chifa",
        "summary": "La branche arm\u00e9e du Hamas a lanc\u00e9 une offensive surprise contre Isra\u00ebl, samedi 7 octobre, suivie de repr\u00e9sailles de Tsahal. Des milliers de personnes ont d\u00e9j\u00e0 perdu la vie. Suivez les \u00e9v\u00e9nements en direct.",
        "link": "https://www.20min.ch/fr/238434023542"
    },
    {
        "title": "La Genevoise Smilla Vallotto remporte son premier troph\u00e9e",
        "summary": "La milieu de terrain de 19 ans a gagn\u00e9 le championnat de Su\u00e8de avec Hammarby, qui devance H\u00e4cken \u00e0 la diff\u00e9rence de buts. L\u2019internationale suisse a d\u00e9livr\u00e9 un assist lors du match d\u00e9cisif.",
        "link": "https://www.20min.ch/fr/541386271079"
    },
    {
        "title": "Un militant vole le micro de Greta Thunberg en plein discours",
        "summary": "L\u2019activiste Greta Thunberg s\u2019est jointe dimanche aux quelque 70\u2019000 participants \u00e0 une marche pour l\u2019environnement \u00e0 Amsterdam. Elle a \u00e9t\u00e9 chahut\u00e9e par un homme envahissant la sc\u00e8ne lors d\u2019un discours. (chs)",
        "link": "https://www.20min.ch/fr/708722596612"
    },
    {
        "title": "Steve Guerdat 2e d\u2019un duel olympique",
        "summary": "Quinze centi\u00e8mes, une paille, entre le champion olympique en titre Ben Maher et son alter ego Steve Guerdat dans le Grand Prix Coupe du monde de V\u00e9rone.",
        "link": "https://www.20min.ch/fr/467561096151"
    },
    {
        "title": "La Sagrada Fam\u00edlia de Barcelone illumine ses nouvelles tours",
        "summary": "La basilique con\u00e7ue par l\u2019architecte catalan Antoni Gaud\u00ed a mis en lumi\u00e8re, dimanche, l\u2019ensemble d\u00e9di\u00e9 aux \u00e9vang\u00e9listes, termin\u00e9 en septembre.",
        "link": "https://www.20min.ch/fr/609651588395"
    },
    {
        "title": "Marine Le Pen exfiltr\u00e9e de la marche contre l\u2019antis\u00e9mitisme \u00e0 Paris",
        "summary": "Sur la place des Invalides dans le 7e arrondissement de Paris, \u00e0 l\u2019occasion de la marche contre l\u2019antis\u00e9mitisme, la pr\u00e9sence de l\u2019extr\u00eame droite provoque des tensions : un groupe de militants de l\u2019organisation juive de gauche Golem essaye de s\u2019opposer au d\u00e9but de la manifestation. Marine Le Pen a \u00e9t\u00e9 exfiltr\u00e9e du cort\u00e8ge vers 17h30, selon \u00abLe Monde\u00bb. (chs)",
        "link": "https://www.20min.ch/fr/760523790111"
    },
    {
        "title": "Retrouvez les r\u00e9sultats des 2e tours au Conseil des Etats",
        "summary": "L\u2019ex-conseiller d\u2019\u00c9tat MCG devance largement son rival socialiste au second tour. La s\u00e9natrice sortante Lisa Mazzone \u00e9vinc\u00e9e, se retire de la politique. Dans le canton de Vaud, Pascal Broulis a battu Rapha\u00ebl Mahaim. Sur Fribourg et Valais, tous les sortants ont \u00e9t\u00e9 r\u00e9\u00e9lus.",
        "link": "https://www.20min.ch/fr/214600516772"
    },
    {
        "title": "\u00abJe faisais des sketchs pour ne pas me faire p\u00e9ter la gueule\u00bb",
        "summary": "Vincent Dedienne est revenu sur son m\u00e9tier de com\u00e9dien dans le \u00abParisien Week-end\u00bb du 11\u00a0novembre 2023. Ado, l\u2019humour est devenu un moyen de d\u00e9fense.",
        "link": "https://www.20min.ch/fr/917899006650"
    },
    {
        "title": "L\u2019Ai Pin de Humane aspire \u00e0 remplacer le smartphone",
        "summary": "La start-up californienne fond\u00e9e par des anciens d\u2019Apple a d\u00e9voil\u00e9 un badge technologique embarquant une IA et capable de projeter des infos sur la paume de la main.",
        "link": "https://www.20min.ch/fr/345493197287"
    },
    {
        "title": "Apr\u00e8s quatre mois de myst\u00e8res, Itzae a \u00e9t\u00e9 pr\u00e9sent\u00e9e au public",
        "summary": "Le zoo Thomas Belt de Juigalpa, au Nicaragua, a pr\u00e9sent\u00e9 aux visiteurs la femelle puma albinos Itzae. Elle est \u00e2g\u00e9e de quatre mois. Le zoo esp\u00e8re d\u00e9sormais attirer les foules. (AFP/atk)",
        "link": "https://www.20min.ch/fr/737689945104"
    },
    {
        "title": "Peter Nygard, ex-magnat de la mode, reconnu coupable par le jury",
        "summary": "Un tribunal de Toronto a estim\u00e9 que Peter Nygard, l\u2019ancien magnat de la mode finno-canadien, a abus\u00e9 d\u2019au moins quatre femmes entre 1988 et 2005.",
        "link": "https://www.20min.ch/fr/791714839206"
    },
    {
        "title": "Record de temp\u00e9rature \u00e0 Rio, en pleine vague de chaleur",
        "summary": "Canicules, incendies, intemp\u00e9ries, tsunamis, s\u00e9ismes, \u00e9ruptions\u2026 Suivez l'actu m\u00e9t\u00e9o et catastrophes naturelles \u00e0 l'international.",
        "link": "https://www.20min.ch/fr/660046508457"
    },
    {
        "title": "Adrian Mannarino rejoint un cercle tr\u00e8s ferm\u00e9",
        "summary": "Vainqueur du tournoi de Sofia, le Fran\u00e7ais de 35 ans a remport\u00e9 son troisi\u00e8me titre de la saison. \u00c0 cet \u00e2ge, seuls les membres du Big 3 ont r\u00e9ussi pareil exploit.",
        "link": "https://www.20min.ch/fr/660833395881"
    },
    {
        "title": "Il saute en parachute et manque de se faire percuter par un avion",
        "summary": "Un accident grave a \u00e9t\u00e9 \u00e9vit\u00e9 de justesse au-dessus de Rio de Janeiro. Un parachutiste a failli se faire percuter par un avion. Personne n\u2019a \u00e9t\u00e9 bless\u00e9. (atk/X)",
        "link": "https://www.20min.ch/fr/786760531256"
    },
    {
        "title": "Toujours sur son nuage, Servette terrasse B\u00e2le",
        "summary": "Les Grenat \u00abmangent\u00bb un FC B\u00e2le r\u00e9duit \u00e0 dix, qui a pourtant men\u00e9 au score. Au d\u00e9but seulement. Sixi\u00e8me succ\u00e8s de suite pour la bande \u00e0 Ren\u00e9 Weiler (4-1).",
        "link": "https://www.20min.ch/fr/280758804078"
    },
    {
        "title": "L\u2019\u00e9change tendu entre Trippier et un supporter",
        "summary": "Le lat\u00e9ral de Newcastle s\u2019est d\u00e9fendu de la d\u00e9faite des siens envers un supporter des Magpies, apr\u00e8s la d\u00e9faite contre Bournemouth samedi (2-0).",
        "link": "https://www.20min.ch/fr/154339554188"
    },
    {
        "title": "\u00abUne \u00e9ruption pourrait arriver n\u2019importe o\u00f9 sur cette fissure\u00bb",
        "summary": "La localit\u00e9 de Grindavik a \u00e9t\u00e9 \u00e9vacu\u00e9e t\u00f4t samedi apr\u00e8s que le d\u00e9placement du magma sous la cro\u00fbte terrestre a entra\u00een\u00e9 des centaines de s\u00e9ismes, faisant craindre une \u00e9ruption volcanique.",
        "link": "https://www.20min.ch/fr/222607248057"
    },
    {
        "title": "Un menu d\u2019un d\u00eener du Titanic vendu pour pr\u00e8s de 93\u2019000 francs",
        "summary": "Le pr\u00e9cieux document avait \u00e9t\u00e9 trouv\u00e9 dans un album photo des ann\u00e9es 1960 apr\u00e8s la mort d\u2019un certain Len Stephenson.",
        "link": "https://www.20min.ch/fr/283974936076"
    },
    {
        "title": "Interruption des soins de la petite Indi, gravement malade",
        "summary": "Suite \u00e0 la d\u00e9cision de la justice britannique vendredi, le b\u00e9b\u00e9 de 8 mois atteint d\u2019une maladie incurable a \u00e9t\u00e9 transf\u00e9r\u00e9 de l\u2019h\u00f4pital sous escorte dans un \u00abhospice\u00bb.",
        "link": "https://www.20min.ch/fr/618860176309"
    },
    {
        "title": "Le producteur de la s\u00e9rie \u00abFauda\u00bb a \u00e9t\u00e9 tu\u00e9 \u00e0 Gaza",
        "summary": "Matan Meir, producteur de la s\u00e9rie diffus\u00e9e sur Netflix, s'\u00e9tait engag\u00e9 aux c\u00f4t\u00e9s de Tsahal pour combattre le Hamas.",
        "link": "https://www.20min.ch/fr/509095781471"
    },
    {
        "title": "Cinq tu\u00e9s dans le crash d\u2019un h\u00e9licopt\u00e8re militaire am\u00e9ricain",
        "summary": "Le commandement europ\u00e9en de l\u2019arm\u00e9e am\u00e9ricaine a d\u00e9voil\u00e9 dimanche le tragique bilan de l\u2019accident a\u00e9rien survenu le 10\u00a0novembre lors d\u2019un entra\u00eenement.",
        "link": "https://www.20min.ch/fr/780625317723"
    },
    {
        "title": "\u00abIl y a tellement d\u2019action et de d\u00e9cors incroyables\u00bb",
        "summary": "La premi\u00e8re de Hunger Games avait lieu jeudi 9 novembre \u00e0 Londres. \u00abLa Ballade du serpent et de l\u2019oiseau chanteur\u00bb sera en salle le 15 novembre prochain.",
        "link": "https://www.20min.ch/fr/897827708401"
    },
    {
        "title": "Cette technique \u00abinfaillible\u00bb pour savoir si votre couple va durer",
        "summary": "Sur TikTok, Alyssa Caribardi a parl\u00e9 du \u00abbird test\u00bb, qui permettrait de savoir \u00e0 quel point vos relations (amicales comme amoureuses) sont susceptibles de fonctionner.\n(Vid\u00e9o: Alyssa Caribardi/fch)",
        "link": "https://www.20min.ch/fr/429622782084"
    },
    {
        "title": "Elle r\u00e9v\u00e8le pourquoi il ne faut pas commander du Coca light dans un avion",
        "summary": "Une h\u00f4tesse de l\u2019air a montr\u00e9 en vid\u00e9o pourquoi verser un Coca-Cola light dans un avion est une tann\u00e9e.\n(Vid\u00e9o: Ariel Cisneros/fch)",
        "link": "https://www.20min.ch/fr/779660320450"
    },
    {
        "title": "Le lion \u00e9chapp\u00e9 qui se baladait dans les rues a \u00e9t\u00e9 arr\u00eat\u00e9",
        "summary": "Les habitants d\u2019une ville italienne pr\u00e8s de Rome ont \u00e9t\u00e9 invit\u00e9s \u00e0 rester chez eux samedi apr\u00e8s-midi pour se garder des crocs d\u2019un lion, \u00e9chapp\u00e9 d\u2019un cirque local et activement recherch\u00e9 par la police. Le fauve a finalement \u00e9t\u00e9 captur\u00e9 dans la soir\u00e9e. (X/cga)",
        "link": "https://www.20min.ch/fr/292469803113"
    },
    {
        "title": "Le Centre continuera de dominer le Conseil des \u00c9tats",
        "summary": "Le PLR esp\u00e9rait affaiblir le Centre \u00e0 la Chambre des cantons. C\u2019est rat\u00e9. Quant aux Verts, ils perdent leur groupe parlementaire.",
        "link": "https://www.20min.ch/fr/608792580065"
    },
    {
        "title": "Mauro Poggia brise l\u2019h\u00e9g\u00e9monie de la gauche genevoise",
        "summary": "Le candidat du MCG si\u00e9gera \u00e0 la Chambre haute du Parlement avec le socialiste Carlo Sommaruga. La Verte Lisa Mazzone va cesser la politique.",
        "link": "https://www.20min.ch/fr/620896164632"
    },
    {
        "title": "Isabelle Chassot et Johanna Gapany r\u00e9\u00e9lues au Conseil des \u00c9tats",
        "summary": "Dimanche, la socialiste Aliz\u00e9e Rey a \u00e9chou\u00e9 de peu \u00e0 d\u00e9loger la sortante PLR Johanna\u00a0Gapany. La centriste Isabelle Chassot a elle \u00e9t\u00e9 r\u00e9\u00e9lue haut la main.",
        "link": "https://www.20min.ch/fr/170832135512"
    },
    {
        "title": "Le duo Maillard-Broulis \u0153uvrera ensemble pour Vaud \u00e0 Berne",
        "summary": "L\u2019ancien conseiller d\u2019\u00c9tat PLR Pascal Broulis est parvenu \u00e0 s\u2019imposer au 2e\u00a0tour du Conseil des \u00c9tats face au Vert Rapha\u00ebl Mahaim. Il rejoindra Pierre-Yves Maillard \u00e9lu au premier tour.",
        "link": "https://www.20min.ch/fr/793038068713"
    },
    {
        "title": "Retrouvez une synth\u00e8se des r\u00e9sultats d\u00e9finitifs",
        "summary": "La Suisse a renouvel\u00e9 son Parlement ce dimanche 22 octobre. Retrouvez ici tous les r\u00e9sultats pour la Suisse et les cantons romands.",
        "link": "https://www.20min.ch/fr/763738733675"
    },
    {
        "title": "En Valais, Philippe Nantermod a bien rat\u00e9 son deuxi\u00e8me tour",
        "summary": "La population valaisanne a soutenu massivement le ticket du Centre, Beat Rieder et Marianne Maret.",
        "link": "https://www.20min.ch/fr/898322608874"
    },
    {
        "title": "Quatre cantons romands \u00e9lisent leurs s\u00e9nateurs ce dimanche",
        "summary": "Les citoyens des cantons de Vaud, Gen\u00e8ve, Fribourg et du Valais doivent choisir dans un second tour qui seront leurs repr\u00e9sentants au Conseil des \u00c9tats \u00e0 Berne.",
        "link": "https://www.20min.ch/fr/963550003993"
    },
    {
        "title": "Isra\u00ebl joue la carte de la dissuasion face au Hezbollah",
        "summary": "Les affrontements sont quotidiens mais limit\u00e9s, entre l\u2019arm\u00e9e isra\u00e9lienne et la milice chiite du Hezbollah, situ\u00e9e au Liban.",
        "link": "https://www.20min.ch/fr/418286746140"
    },
    {
        "title": "Les h\u00f4pitaux de Gaza en passe de se transformer en \u00abmorgues\u00bb",
        "summary": "L\u2019inqui\u00e9tude est \u00e0 son comble dimanche concernant plusieurs h\u00f4pitaux de Gaza soumis \u00e0 des coupures d\u2019\u00e9lectricit\u00e9 et \u00e0 des \u00abattaques\u00bb.",
        "link": "https://www.20min.ch/fr/842864547767"
    },
    {
        "title": "Des arch\u00e9ologues \u00e0 la recherche des restes des victimes du Hamas",
        "summary": "Dans les kibboutz d\u00e9vast\u00e9s par l\u2019attaque du 7 octobre,\u00a0Moshe Ajami et son \u00e9quipe mettent \u00e0 profit des d\u00e9cennies d\u2019exp\u00e9rience leur permettant \u00abd\u2019identifier le plus petit fragment d\u2019os\u00bb.",
        "link": "https://www.20min.ch/fr/790038133559"
    },
    {
        "title": "Les pays arabes et musulmans condamnent, mais ne s\u00e9vissent pas",
        "summary": "R\u00e9unis \u00e0 Riyad pour le sommet conjoint de la Ligue arabe et de l\u2019Organisation de la coop\u00e9ration islamique, les dirigeants ont d\u00e9nonc\u00e9 les actions d\u2019Isra\u00ebl, sans toutefois prendre de mesures.",
        "link": "https://www.20min.ch/fr/955527825831"
    },
    {
        "title": "A Carouge, le PLR garde son si\u00e8ge, \u00e0 Onex, le PS en t\u00eate",
        "summary": "Des \u00e9lections compl\u00e9mentaires avaient lieu dans les deux communes pour remplacer leurs magistrates \u00e9lues ce printemps au Conseil d\u2019Etat.",
        "link": "https://www.20min.ch/fr/811965622043"
    },
    {
        "title": "Le top de l\u2019actu via WhatsApp",
        "summary": "Chaque jour, les cinq articles qui\u00a0ont le plus fait r\u00e9agir sur notre site et notre app peuvent \u00eatre consult\u00e9s via un message envoy\u00e9 sur le r\u00e9seau social.",
        "link": "https://www.20min.ch/fr/438680290708"
    },
    {
        "title": "Une fondation humanitaire genevoise financerait le Hamas",
        "summary": "La Fondation Secours Humanitaire r\u00e9colterait des dons pour le Hamas et aurait re\u00e7u le soutien de parlementaires socialistes genevois, selon la \u00abSonntagsZeitung\u00bb.",
        "link": "https://www.20min.ch/fr/501386115476"
    },
    {
        "title": "Devenez lecteur-reporter, envoyez-nous vos infos",
        "summary": "Vous \u00eates t\u00e9moin d'un \u00e9v\u00e9nement riche en \u00e9motions? Transmettez-nous vos photos et vid\u00e9os via Whatsapp, Telegram, Signal ou Threema. Trois conseils pour faire de supers clich\u00e9s et vid\u00e9os.",
        "link": "https://www.20min.ch/fr/109593009272"
    },
    {
        "title": "Albert R\u00f6sti souhaite une r\u00e9glementation de l\u2019IA",
        "summary": "Dans une interview \u00e0 la \u00abNZZ am Sonntag\u00bb, le conseiller f\u00e9d\u00e9ral UDC estime que la recherche de la v\u00e9rit\u00e9 sera encore plus difficile pour les m\u00e9dias \u00e0 l\u2019avenir.",
        "link": "https://www.20min.ch/fr/692701396110"
    },
    {
        "title": "Un cours pour les seniors qui roulent \u00e0 v\u00e9lo \u00e9lectrique?",
        "summary": "Berne souhaiterait am\u00e9liorer la s\u00e9curit\u00e9 des e-cyclistes, en particulier les plus \u00e2g\u00e9s, en les obligeant \u00e0 un cours de conduite. Pro Senectute y est favorable.",
        "link": "https://www.20min.ch/fr/194274580867"
    },
    {
        "title": "Parapher un PV qu\u2019on ne comprend pas: l\u2019erreur \u00e0 ne pas commettre",
        "summary": "Coll\u00e9 en Suisse al\u00e9manique, un Romand n\u2019avait pas compris la teneur du rapport que la police lui avait fait signer. Les conseils d\u2019un expert pour \u00e9viter ces mauvaises surprises.",
        "link": "https://www.20min.ch/fr/317082014793"
    },
    {
        "title": "L\u2019Allemagne va doubler son aide militaire \u00e0 l\u2019Ukraine en 2024",
        "summary": "La coalition gouvernementale du chancelier Olaf Scholz a pr\u00e9vu de doubler l\u2019aide militaire pr\u00e9vue \u00e0 l\u2019Ukraine en 2024, \u00e0 hauteur de pr\u00e8s de 8\u00a0milliards de francs.",
        "link": "https://www.20min.ch/fr/958401789464"
    },
    {
        "title": "Les images du jour",
        "summary": "Insolites, dr\u00f4les, fortes ou \u00e9mouvantes, les images propos\u00e9es chaque jour par notre r\u00e9daction ne vous laissent pas indiff\u00e9rents.",
        "link": "https://www.20min.ch/fr/854039659326"
    },
    {
        "title": "L\u2019Ukraine doit \u00abse pr\u00e9parer\u00bb aux frappes russes cet hiver",
        "summary": "Suivez l'actualit\u00e9 du conflit et les tensions entre Moscou et l'Occident.",
        "link": "https://www.20min.ch/fr/405723338808"
    },
    {
        "title": "Charles III rend hommage aux soldats britanniques tu\u00e9s au combat",
        "summary": "Le monarque a conduit les c\u00e9r\u00e9monies autour du C\u00e9notaphe, \u00e0 Londres dimanche, sur fond de tensions li\u00e9es au conflit entre Isra\u00ebl et le Hamas.",
        "link": "https://www.20min.ch/fr/248913988528"
    },
    {
        "title": "Ces plats ont toujours \u00e9t\u00e9 v\u00e9g\u00e9taliens",
        "summary": "Le mot \u00abvegan\u00bb suscite souvent des r\u00e9sistances. Adapter ses habitudes alimentaires \u00e0 l\u2019environnement n\u2019est en effet pas du go\u00fbt de tout le monde. Heureusement, bon nombre de plats ne comportent pas d\u2019ingr\u00e9dients d\u2019origine animale \u2013 ou peuvent facilement \u00eatre adapt\u00e9s.",
        "link": "https://www.20min.ch/fr/634462346543"
    },
    {
        "title": "\u00abNous sommes le Airbnb des objets\u00bb",
        "summary": "Accumuler toujours plus de biens nous \u00e9loigne du concept de durabilit\u00e9. Avec sa plateforme, Ivo Kuhn pr\u00f4ne donc l\u2019\u00e9conomie de partage et compte sur l\u2019aide du voisinage.",
        "link": "https://www.20min.ch/fr/977771203287"
    },
    {
        "title": "Migros r\u00e9duit la taille de son administration",
        "summary": "L\u2019assembl\u00e9e des d\u00e9l\u00e9gu\u00e9s de la F\u00e9d\u00e9ration des coop\u00e9ratives Migros (FCM) a clairement d\u00e9cid\u00e9 de faire passer de 23 \u00e0 13 le nombre de membres de son administration.",
        "link": "https://www.20min.ch/fr/459354973914"
    },
    {
        "title": "Airbus envisage de supprimer 750 postes, mais il n'y aura pas de licenciements",
        "summary": "Suivez l'actualit\u00e9 \u00e9conomique en Suisse et dans le monde.",
        "link": "https://www.20min.ch/fr/527977861256"
    },
    {
        "title": "Le superviseur de l\u2019assurance alerte contre l\u2019\u00abarnaque\u00bb Zebrance",
        "summary": "Bas\u00e9e aux \u00c9tats-Unis, la soci\u00e9t\u00e9 d\u2019assurance auto r\u00eave de s\u2019implanter en France. Probl\u00e8me: Zebrance n\u2019a aucune autorisation et \u00abinduit les consommateurs en erreur\u00bb.",
        "link": "https://www.20min.ch/fr/848829554960"
    },
    {
        "title": "Face \u00e0 la pol\u00e9mique, le Premier ministre doit renoncer \u00e0 une hausse de salaire",
        "summary": "Un projet de loi visant \u00e0 augmenter les salaires dans toute l\u2019administration publique japonaise, jusqu\u2019au sommet de l\u2019ex\u00e9cutif, a fait tiquer l\u2019opinion publique.",
        "link": "https://www.20min.ch/fr/311905471410"
    },
    {
        "title": "Sans jouer, la Suisse fait un pas de plus vers l\u2019Euro 2024",
        "summary": "En match en retard du groupe I des qualifications \u00e0 l\u2019Euro 2024, le Kosovo a fait chuter Isra\u00ebl (1-0), principal poursuivant de la Nati. Celle-ci peut valider son ticket pour la phase finale d\u00e8s mercredi.",
        "link": "https://www.20min.ch/fr/973584928621"
    },
    {
        "title": "Justine Mettraux augmente son avantage en t\u00eate",
        "summary": "La navigatrice genevoise et son coskipper Julien Villion ont augment\u00e9 leur avance en t\u00eate de la Transat Jacques Vabre, en cat\u00e9gorie Imoca. En Ultim, l'arriv\u00e9e est proche.",
        "link": "https://www.20min.ch/fr/951972770377"
    },
    {
        "title": "Les Suissesses mal embarqu\u00e9es en qualifications pour l\u2019Euro 2025",
        "summary": "Les joueuses d\u2019Herv\u00e9 Coudray ont conc\u00e9d\u00e9, au Mont\u00e9n\u00e9gro (85-61), une deuxi\u00e8me d\u00e9faite en deux matches dans leur groupe de qualifications pour le Championnat d\u2019Europe 2025.",
        "link": "https://www.20min.ch/fr/238827767903"
    },
    {
        "title": "Le Canada succ\u00e8de \u00e0 la Suisse \u00e0 la Billie Jean King Cup",
        "summary": "Emmen\u00e9 par sa jeune star Leylah Fernandez (21 ans et 35e joueuse mondiale), le Canada a \u00e9cart\u00e9 l'Italie en finale pour devenir champion du monde.",
        "link": "https://www.20min.ch/fr/284412565643"
    },
    {
        "title": "Son coll\u00e8gue veut spoiler \u00abTop Gun\u00bb, un policier sort son arme",
        "summary": "Un agent des forces de l\u2019ordre \u00e9tait jug\u00e9 pour avoir menac\u00e9 de tirer sur un coll\u00e8gue qui voulait d\u00e9voiler la fin d\u2019un film. L\u2019individu a agi en rigolant, mais sa victime est traumatis\u00e9e.",
        "link": "https://www.20min.ch/fr/421598425122"
    },
    {
        "title": "Elle gagne deux fois \u00e0 la loterie \u00e0 une semaine d\u2019intervalle",
        "summary": "Une Am\u00e9ricaine a remport\u00e9 50\u2019000 dollars en jouant sur une application, puis a touch\u00e9 un jackpot de pr\u00e8s d\u2019un million quelques jours apr\u00e8s.",
        "link": "https://www.20min.ch/fr/755708911592"
    },
    {
        "title": "Son c\u0153ur cesse de battre au resto, et le destin s\u2019en m\u00eale",
        "summary": "Un grand-p\u00e8re a \u00e9t\u00e9 victime d\u2019un arr\u00eat cardiaque dans un restaurant d\u2019Orlando, o\u00f9 quatre m\u00e9decins terminaient le repas \u00e0 une table voisine.",
        "link": "https://www.20min.ch/fr/509824574714"
    },
    {
        "title": "\u00abSa t\u00eate \u00e9tait dans la gueule de l\u2019alligator\u00bb",
        "summary": "Une jeune femme qui faisait du snorkeling a \u00e9t\u00e9 attaqu\u00e9e par un saurien de pr\u00e8s de 3\u00a0m\u00e8tres, dimanche en Floride. Elle s\u2019en sort plut\u00f4t bien.",
        "link": "https://www.20min.ch/fr/693946299845"
    },
    {
        "title": "Nicki Minaj regrette certaines de ses chirurgies esth\u00e9tiques",
        "summary": "Complex\u00e9e \u00e0 l\u2019\u00e9poque par son apparence physique, Nicki Minaj a eu recours \u00e0 la chirurgie esth\u00e9tique. Un choix qu\u2019elle semble en partie se reprocher aujourd\u2019hui.",
        "link": "https://www.20min.ch/fr/113562950675"
    },
    {
        "title": "Le compagnon de Caroline Receveur en larmes sur Instagram",
        "summary": "Hugo Philip a post\u00e9 une vid\u00e9o en story o\u00f9 on le voit pleurer. L\u2019amoureux de l\u2019influenceuse qui se bat contre un cancer a expliqu\u00e9 les raisons de sa tristesse.",
        "link": "https://www.20min.ch/fr/426939941015"
    },
    {
        "title": "Le rappeur Kaaris relax\u00e9 d\u2019une accusation de violences conjugales",
        "summary": "Le tribunal a \u00e9cart\u00e9 le motif dont l\u2019accusait son ancienne compagne. Le rappeur a assur\u00e9 n\u2019avoir jamais \u00e9t\u00e9 violent envers les femmes.",
        "link": "https://www.20min.ch/fr/778661519339"
    },
    {
        "title": "Panique chez les fans d\u2019Harry Styles",
        "summary": "Le chanteur est apparu avec la boule \u00e0 z\u00e9ro \u00e0 un concert de U2 \u00e0 Las Vegas. Son nouveau look a laiss\u00e9 ses admiratrices sous le choc.",
        "link": "https://www.20min.ch/fr/654507024544"
    },
    {
        "title": "Nuit Incolore sacr\u00e9 \u00abR\u00e9v\u00e9lation francophone de l\u2019ann\u00e9e\u00bb",
        "summary": "Le chanteur de Fully (VS) a remport\u00e9 vendredi\u00a010 novembre 2023 \u00e0 Cannes le NRJ Music Award de la \u00abR\u00e9v\u00e9lation francophone de l\u2019ann\u00e9e\u00bb.",
        "link": "https://www.20min.ch/fr/332254465049"
    },
    {
        "title": "Kiss diffusera son ultime concert en direct",
        "summary": "Le groupe am\u00e9ricain a choisi un endroit symbolique \u00e0 New York pour la date de fin de sa tourn\u00e9e d\u2019adieux.\u00a0Le show sera diffus\u00e9 en live streaming.",
        "link": "https://www.20min.ch/fr/397307542412"
    },
    {
        "title": "Taylor Swift en Argentine: \u00abElle repr\u00e9sente tout pour nous\u00bb",
        "summary": "Le 9 novembre, l\u2019artiste am\u00e9ricaine a donn\u00e9 le premier de ses trois concerts \u00e0 Buenos Aires, dans le cadre du \u00abThe Eras Tour\u00bb. Certains fans ont saisi l\u2019occasion pour porter un message politique, \u00e0 dix jours d'un scrutin pr\u00e9sidentiel, tr\u00e8s incertain.",
        "link": "https://www.20min.ch/fr/615635258293"
    },
    {
        "title": "Chantre de la techno m\u00e9lodique sous un chapiteau de cirque",
        "summary": "Joris Voorn est une des stars de la 2e \u00e9dition de Zirkuz, les 10 et 11 novembre 2023 \u00e0 la place Bellerive \u00e0 Lausanne. Ce festival m\u00e9lange musique \u00e9lectronique et arts circassiens.",
        "link": "https://www.20min.ch/fr/782612064498"
    },
    {
        "title": "Il sera possible de parler dans une autre langue gr\u00e2ce \u00e0 l\u2019IA",
        "summary": "Le g\u00e9ant sud-cor\u00e9en de la tech Samsung Electronics va d\u00e9ployer un outil de traduction en temps r\u00e9el reposant sur l\u2019intelligence artificielle pour un nouveau smartphone en 2024.",
        "link": "https://www.20min.ch/fr/995216420924"
    },
    {
        "title": "Voici comment cacher son adresse\u00a0IP sur WhatsApp",
        "summary": "Le service de messagerie instantan\u00e9e a lanc\u00e9 une nouvelle option pour prot\u00e9ger la vie priv\u00e9e de ses utilisateurs lors d\u2019appels.",
        "link": "https://www.20min.ch/fr/755040269643"
    },
    {
        "title": "Fin d\u2019Omegle, le populaire site de chat vid\u00e9o entre inconnus",
        "summary": "Le site de discussion par webcam interpos\u00e9e a annonc\u00e9 sa fermeture apr\u00e8s quinze ans d\u2019existence en raison de son utilisation abusive. La plateforme avait re\u00e7u des plaintes de victimes d\u2019abus sexuels en ligne.",
        "link": "https://www.20min.ch/fr/141922990711"
    },
    {
        "title": "TikTok et Instagram se dotent d\u2019un bouton d\u2019alerte",
        "summary": "En France, les utilisateurs des deux r\u00e9seaux sociaux vont pouvoir facilement appeler le num\u00e9ro national d\u2019aide aux victimes de violences num\u00e9riques.",
        "link": "https://www.20min.ch/fr/807559127944"
    },
    {
        "title": "Rockstar Games annonce officiellement \u00abGTA\u00a06\u00bb",
        "summary": "L\u2019\u00e9diteur am\u00e9ricain a confirm\u00e9 la pr\u00e9sentation en d\u00e9cembre d\u2019une bande-annonce de l\u2019un des jeux les plus attendus de ces derni\u00e8res ann\u00e9es, comme anticip\u00e9 quelques heures plus t\u00f4t par Bloomberg.",
        "link": "https://www.20min.ch/fr/628976678390"
    },
    {
        "title": "Faker et T1, seuls contre la Chine",
        "summary": "Les espoirs de la Cor\u00e9e du Sud, o\u00f9 se d\u00e9roulent les Worlds de \u00abLeague of Legends\u00bb, ne sont plus incarn\u00e9s que par T1, face \u00e0 trois \u00e9quipes de l\u2019Empire du Milieu.",
        "link": "https://www.20min.ch/fr/325136345531"
    },
    {
        "title": "Les Saoudiens champions du monde sur \u00abOverwatch 2\u00bb",
        "summary": "L\u2019Arabie saoudite a remport\u00e9 la Coupe du monde du jeu de tir de Blizzard, ce week-end, en battant la Chine en finale.",
        "link": "https://www.20min.ch/fr/740136371292"
    },
    {
        "title": "Cruelle d\u00e9sillusion pour les \u00e9quipes europ\u00e9ennes aux Worlds",
        "summary": "Aucun repr\u00e9sentant du LEC, le championnat europ\u00e9en de \u00abLeague of Legends\u00bb, n\u2019est qualifi\u00e9 pour les play-off des Worlds. G2 et Fnatic ont \u00e9t\u00e9 \u00e9limin\u00e9s par deux teams chinoises, dimanche.",
        "link": "https://www.20min.ch/fr/699713433664"
    },
    {
        "title": "Apr\u00e8s Mario, Nintendo annonce un film sur l\u2019univers de Zelda",
        "summary": "L\u2019univers de \u00abThe Legend of Zelda\u00bb va bient\u00f4t faire son apparition sur grand \u00e9cran. Aucune date n\u2019a encore \u00e9t\u00e9 communiqu\u00e9e sur sa sortie.",
        "link": "https://www.20min.ch/fr/477980442776"
    },
    {
        "title": "\u00abLes r\u00e9actions sexistes ne m\u2019inqui\u00e8tent pas\u00bb",
        "summary": "Nia DaCosta, r\u00e9alisatrice de \u00abThe Marvels\u00bb, esp\u00e8re que son film mettant en sc\u00e8ne trois superh\u00e9ro\u00efnes inspirera le public f\u00e9minin.",
        "link": "https://www.20min.ch/fr/759101801786"
    },
    {
        "title": "Le film \u00abBarbenheimer\u00bb va voir le jour",
        "summary": "Une com\u00e9die d\u00e9jant\u00e9e s\u2019inspirant des films \u00abBarbie\u00bb et \u00abOppenheimer\u00bb sortira en salle en 2024. Le casting de cette parodie reste encore inconnu.",
        "link": "https://www.20min.ch/fr/194860791612"
    },
    {
        "title": "Dua Lipa est pr\u00eate pour \u00abBarbie 2\u00bb",
        "summary": "La chanteuse, qui a sign\u00e9 une chanson de la bande originale du film et y incarne une Barbie sir\u00e8ne, se verrait bien jouer dans une suite.",
        "link": "https://www.20min.ch/fr/193212102224"
    },
    {
        "title": "Quel est l\u2019\u00e9cart d\u2019\u00e2ge id\u00e9al entre deux enfants?",
        "summary": "L\u2019\u00e9cart d\u2019\u00e2ge influence la relation des membres d\u2019une fratrie. D\u2019autres aspects tels que la sant\u00e9, l\u2019\u00e9ducation ou la dur\u00e9e du mariage des parents entrent aussi en ligne de compte.",
        "link": "https://www.20min.ch/fr/592740580308"
    },
    {
        "title": "Un mannequin asiatique se d\u00e9couvre blanchi par une IA",
        "summary": "Le couturier Michael Costello a publi\u00e9 sur Instagram une photo de Shereen Wu lors de son d\u00e9fil\u00e9. Probl\u00e8me: les traits du mannequin ont \u00e9t\u00e9 modifi\u00e9s.",
        "link": "https://www.20min.ch/fr/308425523116"
    },
    {
        "title": "Viagra: un moyen simple pour s\u2019en passer",
        "summary": "L\u2019activit\u00e9 physique d\u2019endurance serait aussi efficace que les m\u00e9dicaments pour lutter contre les troubles de l\u2019\u00e9rection, selon une \u00e9quipe de chercheurs am\u00e9ricains.",
        "link": "https://www.20min.ch/fr/833124826257"
    },
    {
        "title": "Quand vous gal\u00e9rez pour vous lever le matin\u2026",
        "summary": "Apr\u00e8s avoir retrouv\u00e9 l\u2019heure d\u2019hiver, nombreux sont ceux qui se plaignent de fatigue. Voici quelques conseils qui vous aideront \u00e0 vous r\u00e9veiller.",
        "link": "https://www.20min.ch/fr/242268887068"
    },
    {
        "title": "Le c\u00e2lin est factur\u00e9 150 balles de l\u2019heure",
        "summary": "Cuddlist est une entreprise am\u00e9ricaine dont les employ\u00e9s sont pay\u00e9s pour enlacer la client\u00e8le. Celle-ci est essentiellement compos\u00e9e d\u2019hommes mari\u00e9s.",
        "link": "https://www.20min.ch/fr/226606524872"
    },
    {
        "title": "38\u00a0tonnes de v\u00eatements balanc\u00e9es pendant le marathon de New York",
        "summary": "La c\u00e9l\u00e8bre course fait r\u00eaver beaucoup d\u2019aficionados de cette discipline. Elle g\u00e9n\u00e8re n\u00e9anmoins une quantit\u00e9 astronomique de d\u00e9chets.",
        "link": "https://www.20min.ch/fr/115365878166"
    },
    {
        "title": "Une princesse peut cacher une reine du camouflage",
        "summary": "Kate Middleton, \u00e9lev\u00e9e au grade de colonel en chef, a particip\u00e9 \u00e0 un exercice avec son r\u00e9giment, dans le Norfolk. Les femmes des familles r\u00e9gnantes s\u2019affichent en uniforme.",
        "link": "https://www.20min.ch/fr/821594511227"
    },
    {
        "title": "Les fesses de Kendall Jenner \u00e0 la place du sapin de No\u00ebl",
        "summary": "Le mannequin a \u00e9t\u00e9 critiqu\u00e9 apr\u00e8s avoir pos\u00e9 d\u00e9nud\u00e9 pour une marque de v\u00eatements. Des internautes s\u2019insurgent contre la femme-objet.",
        "link": "https://www.20min.ch/fr/978759203094"
    },
    {
        "title": "La mani\u00e8re dont vous portez vos chaussettes en dit long sur votre g\u00e9n\u00e9ration",
        "summary": "La diff\u00e9rence entre la g\u00e9n\u00e9ration Z et la g\u00e9n\u00e9ration des millennials se lit, soi-disant, au niveau des\u2026 pieds. Explications.",
        "link": "https://www.20min.ch/fr/767871085560"
    },
    {
        "title": "Huit destinations de vacances grandioses pour petits budgets",
        "summary": "L\u2019\u00e9vasion sans avoir \u00e0 casser sa tirelire. Un guide de voyage propose des destinations tendance pour 2024 qui ne n\u00e9cessitent pas de gros moyens financiers.",
        "link": "https://www.20min.ch/fr/166796497263"
    },
    {
        "title": "Un bouton secret permet de relever l\u2019accoudoir",
        "summary": "Devenue virale, la vid\u00e9o d\u2019une h\u00f4tesse de l\u2019air pr\u00e9sente une astuce que peu de passagers connaissent.",
        "link": "https://www.20min.ch/fr/807720258008"
    },
    {
        "title": "Classement des lieux les moins touristiques du monde",
        "summary": "Si vous envisagez de passer vos prochaines vacances loin du tumulte et de la foule, id\u00e9alement sur une \u00eele d\u00e9serte, vous feriez bien de consid\u00e9rer ces destinations. Elles sont les moins visit\u00e9es du monde.",
        "link": "https://www.20min.ch/fr/142700922172"
    },
    {
        "title": "Pourquoi les compagnies a\u00e9riennes veulent vous voir souffrir en vol",
        "summary": "Si vous avez d\u00e9j\u00e0 \u00e9t\u00e9 victime d\u2019une mauvaise exp\u00e9rience en avion, vous vous \u00eates peut-\u00eatre d\u00e9j\u00e0 offert un surclassement sur le vol suivant. Et c\u2019est pr\u00e9cis\u00e9ment le but recherch\u00e9 par les compagnies a\u00e9riennes.",
        "link": "https://www.20min.ch/fr/382769203248"
    },
    {
        "title": "Quatre bons plans pour visiter la Colombie",
        "summary": "Bogot\u00e1 est un lieu o\u00f9 se m\u00ealent les traditions colombiennes et les caract\u00e9ristiques d\u2019une m\u00e9tropole moderne. C\u2019est parti pour une visite de la ville, avec au programme une d\u00e9gustation de cacao, un menu de 18 plats et un jeu d\u00e9tonant.",
        "link": "https://www.20min.ch/fr/866854275565"
    },
    {
        "title": "Voici comment se masturber avec des ongles longs",
        "summary": "Se donner du plaisir, ramasser une pi\u00e8ce ou ouvrir une canette peut\u00a0\u00eatre compliqu\u00e9 avec des griffes imposantes. Ces quelques astuces simples vous aideront \u00e0 y parvenir.",
        "link": "https://www.20min.ch/fr/574989415995"
    },
    {
        "title": "245\u00a0francs le parfum pour b\u00e9b\u00e9",
        "summary": "Dior lance une collection de cosm\u00e9tiques pour les tout-petits. La gamme compl\u00e8te co\u00fbte plus de 500\u00a0francs.",
        "link": "https://www.20min.ch/fr/603034362040"
    },
    {
        "title": "Votez pour la moustache la plus dingue",
        "summary": "Peroxyd\u00e9, sculptural ou ultrafin, cet attribut masculin joue l\u2019originalit\u00e9. Donnez votre avis.",
        "link": "https://www.20min.ch/fr/816894007769"
    },
    {
        "title": "Hausse des ventes de d\u00e9odorants avec la fin du t\u00e9l\u00e9travail",
        "summary": "Le retour du travail en pr\u00e9sentiel pousserait les employ\u00e9s \u00e0 utiliser davantage de d\u00e9odorant.",
        "link": "https://www.20min.ch/fr/995195376025"
    },
    {
        "title": "Millie Bobby Brown d\u00e9voile son acn\u00e9",
        "summary": "La star de \u00abStranger Things\u00bb a post\u00e9 une photo de ses boutons, sur Instagram. Cette d\u00e9marche a s\u00e9duit ses fans.",
        "link": "https://www.20min.ch/fr/200127645384"
    },
    {
        "title": "Elle laisse ses fils grossir pour ne pas utiliser le chauffage",
        "summary": "Une tiktokeuse livre ses astuces pour ne pas avoir froid chez soi cet hiver. Parmi elles, celle de laisser ses enfants prendre du poids pour se constituer une r\u00e9serve \u00e9nerg\u00e9tique.",
        "link": "https://www.20min.ch/fr/549602870907"
    },
    {
        "title": "Ce millionnaire construit des maisonnettes pour sans-abris",
        "summary": "Un entrepreneur canadien a d\u00e9cid\u00e9 d\u2019utiliser sa fortune pour la bonne cause. Gr\u00e2ce \u00e0 lui, les sans-abris auront d\u00e9sormais un toit au-dessus de la t\u00eate. Rencontre.",
        "link": "https://www.20min.ch/fr/873343977759"
    },
    {
        "title": "Ne jetez plus vos collants fil\u00e9s",
        "summary": "Il suffit d\u2019un accroc pour qu\u2019on les exp\u00e9die tout droit \u00e0 la poubelle. Pourtant des bas fil\u00e9s peuvent encore servir.",
        "link": "https://www.20min.ch/fr/504393911971"
    },
    {
        "title": "Ces six calendriers de l\u2019avent sortent de l\u2019ordinaire",
        "summary": "\u00c0 moins d\u2019un mois de l\u2019ouverture de la premi\u00e8re porte, voici des id\u00e9es pour vous inspirer. Accessoires \u00e9rotiques ou fromages, il y en a pour tous les go\u00fbts.",
        "link": "https://www.20min.ch/fr/592485762338"
    },
    {
        "title": "Durabilit\u00e9: quel emballage choisir?",
        "summary": "Voici une comparaison des emballages alimentaires pr\u00e9sents dans les rayons afin de d\u00e9terminer quels produits sont les moins nuisibles \u00e0 l\u2019environnement.",
        "link": "https://www.20min.ch/fr/121006142906"
    },
    {
        "title": "Ces aliments sont les plus nocifs pour l\u2019environnement",
        "summary": "Impossible de faire l\u2019impasse sur l\u2019alimentation quand on se soucie du climat. Voici une liste d\u2019aliments particuli\u00e8rement nuisibles pour l\u2019environnement et quelques alternatives.",
        "link": "https://www.20min.ch/fr/376535025195"
    },
    {
        "title": "Nouveau en Suisse romande: une bo\u00eete \u00e0 pizza r\u00e9utilisable",
        "summary": "Des pizzerias proposent un conditionnement \u00e0 la place du carton. La soci\u00e9t\u00e9 Recircle, qui lance cette op\u00e9ration, estime qu\u2019en Suisse 40\u00a0millions de bo\u00eetes finissent \u00e0 la poubelle, chaque ann\u00e9e.",
        "link": "https://www.20min.ch/fr/205895791234"
    },
    {
        "title": "Le lait, un textile qui ressemble \u00e0 la soie",
        "summary": "Du lait pour cr\u00e9er du tissu? Des marques con\u00e7oivent des v\u00eatements avec cette nouvelle mati\u00e8re naturelle.",
        "link": "https://www.20min.ch/fr/531607415367"
    },
    {
        "title": "\u00c9tiqueter la viande comme les cigarettes pour en manger moins",
        "summary": "Une \u00e9tude montre que la consommation de viande diminue si elle contient un message de pr\u00e9vention comme sur les paquets de cigarettes.",
        "link": "https://www.20min.ch/fr/768342619522"
    },
    {
        "title": "Il faut \u00e9viter de manger des fruits le soir: vrai ou faux?",
        "summary": "Selon une croyance r\u00e9pandue, la consommation de fruits avant le coucher nuit au bien-\u00eatre. Qu\u2019en est-il vraiment?",
        "link": "https://www.20min.ch/fr/653933891844"
    },
    {
        "title": "Savez-vous comment poussent ces aliments?",
        "summary": "Nous consommons certains aliments, sans pour autant savoir comment ils sont cultiv\u00e9s. Saviez-vous, par exemple, que l\u2019ananas poussait sur une tige? D\u2019autres plantes pourraient bien vous surprendre.",
        "link": "https://www.20min.ch/fr/593993839393"
    },
    {
        "title": "Le PSG sort un livre avec les recettes de cuisine pr\u00e9f\u00e9r\u00e9es des joueurs",
        "summary": "Le club de football parisien a collabor\u00e9 avec un chef doublement \u00e9toil\u00e9 et un nutritionniste pour r\u00e9diger \u00ab\u00c0 table avec le Paris Saint-Germain\u00bb.",
        "link": "https://www.20min.ch/fr/321598794238"
    },
    {
        "title": "Que faire si on est coinc\u00e9 \u00e0 un passage \u00e0 niveau?",
        "summary": "Comment r\u00e9agir dans cette situation stressante? Les experts en mobilit\u00e9 Viva r\u00e9pondent \u00e0 cette question pos\u00e9e par un lecteur.",
        "link": "https://www.20min.ch/fr/808412622904"
    },
    {
        "title": "O\u00f9 les pneus neige sont-ils obligatoires?",
        "summary": "Les pneus d\u2019hiver ne sont pas obligatoires en Suisse, contrairement \u00e0 d\u2019autres pays europ\u00e9ens, dans lesquels les contrevenants risquent des amendes sal\u00e9es.",
        "link": "https://www.20min.ch/fr/984170704614"
    },
    {
        "title": "\u00c0 quel point le chargement peut-il d\u00e9passer?",
        "summary": "Voiture trop petite ou chargement trop grand: de nombreux automobilistes font preuve de cr\u00e9ativit\u00e9 pour transporter des chargements. Ils jouent \u00e0 Tetris avec des objets volumineux, ce qui est dangereux et pourrait leur valoir une amende sal\u00e9e. \u00c0 certaines conditions, il est tout de m\u00eame possible de transporter un certain volume.",
        "link": "https://www.20min.ch/fr/803479732306"
    },
    {
        "title": "Ce 4x4 est la version r\u00e9duite d\u2019une voiture iconique",
        "summary": "Mercedes pr\u00e9voit de d\u00e9cliner la Classe G en un mod\u00e8le plus petit. Le constructeur se garde toutefois de d\u00e9voiler le design du nouveau v\u00e9hicule.",
        "link": "https://www.20min.ch/fr/842702804531"
    },
    {
        "title": "Gagne tes billets pour l\u2019exposition \u00ab Tintin l\u2019aventure immersive \u00bb",
        "summary": "Tente ta chance et gagne peut-\u00eatre tes billets pour l\u2019exposition \u00abTintin l\u2019aventure immersive\u00bb qui a lieu du 13 octobre 2023 au 11 f\u00e9vrier 2024 \u00e0\u00a0 Beaulieu, Lausanne.",
        "link": "https://www.20min.ch/fr/439204730306"
    },
    {
        "title": "Gagne tes billets pour Aime Simone",
        "summary": "Tente ta chance et gagne peut-\u00eatre tes billets pour le concert de Aime Simone, qui aura lieu le 26 novembre aux Docks \u00e0 Lausanne.",
        "link": "https://www.20min.ch/fr/170698607512"
    },
    {
        "title": "Gagne tes billets pour le cin\u00e9-concert Naruto Symphonic Experience",
        "summary": "Tente ta chance et gagne peut-\u00eatre deux billets pour assister au cin\u00e9-concert \u00e9v\u00e9nement Naruto Symphonic Experience qui aura lieu le 10 d\u00e9cembre \u00e0 l\u2019Arena de Gen\u00e8ve.",
        "link": "https://www.20min.ch/fr/183769193563"
    },
    {
        "title": "Gagne un week-end de ski-wellness \u00e0 Zermatt pour deux personnes",
        "summary": "Ressens-tu un profond d\u00e9sir de vivre des aventures palpitantes \u00e0 la neige et des moments douillets en montagne? Durant cinq semaines, les amoureux de l\u2019hiver ont la possibilit\u00e9 de participer \u00e0 notre tirage au sort et de gagner des prix incroyables pour cinq r\u00e9gions de montagne suisses. Nous mettons notamment en jeu des packs ski et un week-end bien-\u00eatre dans l\u2019exquise r\u00e9gion de Zermatt.",
        "link": "https://www.20min.ch/fr/894372756849"
    },
    {
        "title": "Gagne un week-end de ski-wellness \u00e0 Ovronnaz pour deux personnes",
        "summary": "Envie d\u2019aventures inoubliables sur les pistes et d\u2019une touche de luxe au beau milieu des montagnes? Durant cinq semaines, nous mettons en jeu des prix attrayants pour cinq r\u00e9gions de montagne suisses, qui raviront le c\u0153ur de tous les fans d\u2019hiver! Nous offrons notamment des packs ski et un week-end bien-\u00eatre dans la superbe r\u00e9gion d\u2019Ovronnaz.",
        "link": "https://www.20min.ch/fr/105642900602"
    },
    {
        "title": "Les enfants d\u2019Asie du Sud les plus touch\u00e9s par la p\u00e9nurie d\u2019eau",
        "summary": "En 2022 45\u00a0millions d\u2019enfants n\u2019avaient pas acc\u00e8s \u00e0 des services d\u2019eau potable de base en Asie du Sud, soit davantage que dans toute autre r\u00e9gion du globe.",
        "link": "https://www.20min.ch/fr/154329886808"
    },
    {
        "title": "Washington sera un \u00abbon h\u00f4te\u00bb pour la Russie au sommet de l\u2019Apec",
        "summary": "Si les \u00c9tats-Unis ont refus\u00e9 la venue de Vladimir Poutine pour le sommet de l\u2019Asie-Pacifique, la Russie ne sera pas mise \u00e0 l\u2019\u00e9cart cette semaine \u00e0 San Francisco.",
        "link": "https://www.20min.ch/fr/301471083628"
    },
    {
        "title": "Dure joute entre Sergio Massa et Javier Milei avant le scrutin",
        "summary": "\u00c0 une semaine du second tour de l\u2019\u00e9lection pr\u00e9sidentielle en Argentine, Sergio Massa et Javier Milei ont eu un d\u00e9bat tr\u00e8s anim\u00e9 dimanche.",
        "link": "https://www.20min.ch/fr/711900310022"
    },
    {
        "title": "Macron-Berset \u00e0 l\u2019UNIL: entre b\u00e2timent boucl\u00e9 et chiens renifleurs",
        "summary": "La venue des pr\u00e9sidents suisse et fran\u00e7ais jeudi \u00e0 l\u2019Universit\u00e9 de Lausanne va perturber la tranquillit\u00e9 du campus, dispositif de s\u00e9curit\u00e9 oblige.",
        "link": "https://www.20min.ch/fr/742616632872"
    },
    {
        "title": "\u00abJ\u2019ai d\u00e9couvert \u00abHunger Games\u00bb \u00e0 l\u2019\u00e9cole\u00bb",
        "summary": "R\u00e9v\u00e9l\u00e9e par la s\u00e9rie \u00abEuphoria\u00bb, Hunter Schafer joue le r\u00f4le de Tigris dans \u00abHunger Games: La Ballade du serpent et de l\u2019oiseau chanteur\u00bb, au cin\u00e9ma d\u00e8s le 15\u00a0novembre 2023.",
        "link": "https://www.20min.ch/fr/200336137422"
    },
    {
        "title": "Une \u00abpattes-patrouille\u00bb apaise les voyageurs dans l\u2019a\u00e9roport \u00abmaudit\u00bb",
        "summary": "Trois chiens affectueux patrouillent dans l\u2019a\u00e9roport international de Berlin. Leur mission est d\u2019apaiser les voyageurs \u00e0 bout de nerfs, particuli\u00e8rement en p\u00e9riode de d\u00e9part en vacances. (AFP/ast)",
        "link": "https://www.20min.ch/fr/266731596919"
    },
    {
        "title": "Un dirigeant a voulu entrer de force dans la cabine de la VAR",
        "summary": "Au Br\u00e9sil, le directeur sportif des Corinthians n'a pas appr\u00e9ci\u00e9 une d\u00e9cision des arbitres \u00e0 la vid\u00e9o et a voulu le faire savoir. Mais ils n'\u00e9taient pas l\u00e0.",
        "link": "https://www.20min.ch/fr/893179098713"
    },
    {
        "title": "Ne faites pas la sourde oreille quand vous entendez ces bruits",
        "summary": "Des interrupteurs qui gr\u00e9sillent et des toilettes qui gargouillent peuvent indiquer la pr\u00e9sence de probl\u00e8mes sous-jacents, voire de dangers imminents.",
        "link": "https://www.20min.ch/fr/382187847746"
    },
    {
        "title": "Le s\u00e9nateur Tim Scott se retire de la course \u00e0 la pr\u00e9sidentielle",
        "summary": "Apr\u00e8s l\u2019ancien vice-pr\u00e9sident des \u00c9tats-Unis, Mike Pence, Tim Scott est le deuxi\u00e8me candidat \u00e0 se retirer\u00a0de la course \u00e0 l\u2019investiture r\u00e9publicaine.",
        "link": "https://www.20min.ch/fr/495238017452"
    },
    {
        "title": "L\u2019humoriste fran\u00e7ais Guillaume Meurice persiste",
        "summary": "Sanctionn\u00e9 d\u2019un avertissement, le chroniqueur sur France Inter a repris l\u2019antenne dimanche soir en revenant sur ses propos qui lui avaient valu des accusations d\u2019antis\u00e9mitisme.",
        "link": "https://www.20min.ch/fr/941196858134"
    },
    {
        "title": "Les 40 ouvriers pi\u00e9g\u00e9s dans un tunnel effondr\u00e9 sont vivants",
        "summary": "Les sauveteurs ont pu entrer en contact avec les travailleurs coinc\u00e9s depuis dimanche. Ils ont pu injecter de l\u2019oxyg\u00e8ne dans la zone effondr\u00e9e du tunnel et faire p\u00e9n\u00e9trer de la nourriture.",
        "link": "https://www.20min.ch/fr/951494131935"
    },
    {
        "title": "Mal \u00e0 l\u2019aise avec des \u00absquatteurs\u00bb, une \u00c9glise ferme temporairement",
        "summary": "Une poign\u00e9e de sans-abris avaient pris leurs aises dans une \u00e9glise lausannoise, irritant des fid\u00e8les. Le lieu a \u00e9t\u00e9 \u00e9vacu\u00e9 et boucl\u00e9, avant qu\u2019une d\u00e9cision soit prise, lundi soir.",
        "link": "https://www.20min.ch/fr/625465828698"
    },
    {
        "title": "L\u2019Etna se r\u00e9veille: des fontaines de lave jaillissent de son crat\u00e8re",
        "summary": "Le volcan sicilien s\u2019anime depuis quelques jours. Les autorit\u00e9s ont fait pass\u00e9 le niveau d\u2019alerte de jaune \u00e0 orange. Aucun d\u00e9g\u00e2t n\u2019a encore \u00e9t\u00e9 enregistr\u00e9. (AFP/AP/atk)",
        "link": "https://www.20min.ch/fr/478561862881"
    },
    {
        "title": "Une farouche opposante \u00e0 Duterte lib\u00e9r\u00e9e sous caution",
        "summary": "La militante des droits humains Leila de Lima est sortie de prison lundi, pr\u00e8s de sept ans apr\u00e8s son incarc\u00e9ration controvers\u00e9e.",
        "link": "https://www.20min.ch/fr/477013487617"
    },
    {
        "title": "Novak Djokovic assur\u00e9 de finir l\u2019ann\u00e9e comme No 1",
        "summary": "Le Serbe a assur\u00e9 l\u2019essentiel face \u00e0 Holger Rune. Il terminera la saison au sommet du classement ATP pour la huiti\u00e8me fois de sa carri\u00e8re.",
        "link": "https://www.20min.ch/fr/214557410783"
    },
    {
        "title": "Matthew Perry aurait replong\u00e9 dans la drogue avant de mourir",
        "summary": "Kayti Edwards, une ancienne petite amie de l'interpr\u00e8te de Chandler Bing dans \u00abFriends\u00bb, explique avoir rep\u00e9r\u00e9 des signaux indiquant que l'acteur n'\u00e9tait pas sobre dans les jours qui ont pr\u00e9c\u00e9d\u00e9 sa mort.",
        "link": "https://www.20min.ch/fr/261093680039"
    },
    {
        "title": "Il se remet l\u2019\u00e9paule \u00e0 l\u2019aide de son v\u00e9lo en pleine course",
        "summary": "Sc\u00e8ne improbable \u00e0 Niel: lors de la 3e manche du Superprestige, Lars van der Haar s\u2019est remis l\u2019\u00e9paule droite en pleine course \u00e0 l\u2019aide de son v\u00e9lo.",
        "link": "https://www.20min.ch/fr/438387185608"
    },
    {
        "title": "Des retrouvailles sous le signe de \u00abla paix et du d\u00e9veloppement\u00bb",
        "summary": "Les pr\u00e9sidents am\u00e9ricain et chinois se retrouvent mercredi pour la premi\u00e8re fois depuis pr\u00e8s d\u2019un an, en marge du sommet de la Coop\u00e9ration \u00e9conomique pour l\u2019Asie-Pacifique en Californie.",
        "link": "https://www.20min.ch/fr/295695206124"
    },
    {
        "title": "Trois hommes ex\u00e9cut\u00e9s pour \u00abactes de terrorisme\u00bb",
        "summary": "Reconnus coupables d\u2019avoir coop\u00e9r\u00e9 avec un groupe jihadiste, trois individus ont \u00e9t\u00e9 pendus lundi dans le sud-est du pays.",
        "link": "https://www.20min.ch/fr/514878864285"
    },
    {
        "title": "Bryan Colon revient aux Lions de Gen\u00e8ve",
        "summary": "En fin de convalescence apr\u00e8s une grave blessure au genou, l\u2019ancien capitaine des Lions a sign\u00e9 avec le club du bout du lac.",
        "link": "https://www.20min.ch/fr/561627577386"
    },
    {
        "title": "Travis Barker joue de la batterie pour son b\u00e9b\u00e9",
        "summary": "Le batteur de Blink-182 a post\u00e9 une vid\u00e9o de lui en train de jouer des baguettes pour le gar\u00e7on qu\u2019il a eu avec Kourtney Kardashian.",
        "link": "https://www.20min.ch/fr/254259674298"
    },
    {
        "title": "Rishi Sunak a limog\u00e9 sa ministre de l\u2019Int\u00e9rieur",
        "summary": "Suella Braverman, au c\u0153ur de plusieurs pol\u00e9miques, notamment apr\u00e8s avoir critiqu\u00e9 la police et les migrants, est remplac\u00e9e par l\u2019actuel ministre des Affaires \u00e9trang\u00e8res James Cleverly.",
        "link": "https://www.20min.ch/fr/569619227329"
    },
    {
        "title": "La petite Indi s\u2019est \u00e9teinte: \u00abNous avons honte et le c\u0153ur bris\u00e9\u00bb",
        "summary": "Au c\u0153ur d\u2019une bataille judiciaire entre ses parents et le personnel soignant, une petite fille de 8\u00a0mois qui \u00e9tait atteinte d\u2019une maladie incurable est d\u00e9c\u00e9d\u00e9e lundi apr\u00e8s l\u2019arr\u00eat des soins.",
        "link": "https://www.20min.ch/fr/613405362456"
    },
    {
        "title": "Ana\u00efs Camizuli agress\u00e9e en bo\u00eete de nuit",
        "summary": "La candidate de t\u00e9l\u00e9r\u00e9alit\u00e9 a \u00e9t\u00e9 frapp\u00e9e par un homme dans la nuit du 10 au 11 novembre 2023. Le visage tum\u00e9fi\u00e9, elle a d\u00e9nonc\u00e9 cette violence gratuite sur les r\u00e9seaux.",
        "link": "https://www.20min.ch/fr/956544640603"
    },
    {
        "title": "Qui porte le mieux la robe noire?",
        "summary": "Demi Lovato, Kim Kardashian ou encore Heidi Klum ont rivalis\u00e9 d\u2019\u00e9l\u00e9gance sur le tapis rouge d\u2019un gala de charit\u00e9 ce week-end. Donnez votre avis.",
        "link": "https://www.20min.ch/fr/156061962729"
    },
    {
        "title": "Au Texas, un lyc\u00e9e accueille les adolescentes avec leur b\u00e9b\u00e9",
        "summary": "Reportage dans l\u2019un des \u00c9tat conservateurs ayant d\u00e9clar\u00e9 l\u2019avortement ill\u00e9gal suite \u00e0 une d\u00e9cision historique de la Cour supr\u00eame am\u00e9ricaine.",
        "link": "https://www.20min.ch/fr/334590754747"
    },
    {
        "title": "Une nouvelle norme internationale pour encadrer les crypto-actifs",
        "summary": "La Suisse fait partie des pays signataires pour la mise en \u0153uvre d\u00e8s 2027 de cette nouvelle norme internationale sur l\u2019\u00e9change automatique d\u2019informations entre autorit\u00e9s fiscales.",
        "link": "https://www.20min.ch/fr/530676626721"
    },
    {
        "title": "Karin Keller-Sutter veut limiter le tourisme d\u2019achat",
        "summary": "\u00c0 l\u2019avenir, la franchise pour importer des marchandises pourrait passer de 300 \u00e0 150 fr. La ministre des Finances veut faire avancer le dossier et proc\u00e9der \u00e0 des consultations.",
        "link": "https://www.20min.ch/fr/445872342301"
    },
    {
        "title": "L\u2019ancien Premier ministre David Cameron revient au gouvernement",
        "summary": "Sept ans apr\u00e8s avoir d\u00e9clench\u00e9 le r\u00e9f\u00e9rendum sur le Brexit, l\u2019ex-Premier ministre prend la t\u00eate des Affaires \u00e9trang\u00e8res, \u00e0 la place de James Cleverly, nomm\u00e9 \u00e0 l\u2019Int\u00e9rieur.",
        "link": "https://www.20min.ch/fr/108456024612"
    },
    {
        "title": "Partouzes entre gardiens dans la plus grande prison du pays",
        "summary": "L\u2019\u00e9tablissement p\u00e9nitentiaire de Lantin est actuellement \u00e9clabouss\u00e9 par un scandale sexuel. Le directeur s\u2019est vu contraint de recadrer ses \u00e9quipes.",
        "link": "https://www.20min.ch/fr/678072132673"
    },
    {
        "title": "Kiev sur le point de percer les lignes russes? Le Kremlin muet",
        "summary": "L\u2019Ukraine serait en train de consolider des positions sur la rive gauche du fleuve Dniepr. Des informations que ne confirme pas la Russie.",
        "link": "https://www.20min.ch/fr/348631889698"
    },
    {
        "title": "L\u2019Islande retient son souffle et se pr\u00e9pare \u00e0 une \u00e9ruption \u00abdans les heures qui viennent\u00bb",
        "summary": "Le d\u00e9placement de magma sous le manteau terrestre ou les nombreuses secousses sismiques sont autant de signes qui inqui\u00e8tent les autorit\u00e9s islandaises. La peur d\u2019un \u00e9pisode comme celui de 2010 se fait ressentir...\n(Vid\u00e9o: AFP/fch)",
        "link": "https://www.20min.ch/fr/214661827346"
    },
    {
        "title": "Tacl\u00e9 par Britney Spears, Justin pourrait riposter en musique",
        "summary": "La chanteuse n\u2019a pas \u00e9t\u00e9 tendre dans ses m\u00e9moires avec celui qui a partag\u00e9 sa vie de 1999 \u00e0 2002. Justin Timberlake serait en train de pr\u00e9parer un morceau en guise de r\u00e9ponse.",
        "link": "https://www.20min.ch/fr/182338552306"
    },
    {
        "title": "Le Kenya d\u00e9cr\u00e8te un jour f\u00e9ri\u00e9 pour\u2026 planter des arbres",
        "summary": "Le pr\u00e9sident William Ruto s\u2019est engag\u00e9 \u00e0 ce que 15\u00a0milliards d\u2019arbres soient plant\u00e9s d\u2019ici 2032, pour renforcer la couverture foresti\u00e8re du pays.",
        "link": "https://www.20min.ch/fr/406645618832"
    },
    {
        "title": "Le courrier n\u2019est plus distribu\u00e9 dans certaines zones",
        "summary": "Faute de personnel, La Poste ne passe plus que tous les dix ou quinze jours dans plusieurs secteurs d'Annemasse. Mais la situation s\u2019am\u00e9liorerait.",
        "link": "https://www.20min.ch/fr/319565620375"
    },
    {
        "title": "En 24\u00a0heures, plus de 200 migrants ont \u00e9t\u00e9 secourus dans\u00a0la Manche",
        "summary": "Plusieurs op\u00e9rations de sauvetage ont \u00e9t\u00e9 men\u00e9es ce week-end, par des navires affr\u00e9t\u00e9s par la France, a annonc\u00e9 lundi la pr\u00e9fecture de la Manche.",
        "link": "https://www.20min.ch/fr/703673050549"
    },
    {
        "title": "Cesc Fabregas se lance dans le coaching \u00e0 C\u00f4me",
        "summary": "L\u2019ancien international espagnol a \u00e9t\u00e9 nomm\u00e9 pour remplacer\u00a0Moreno Longo, sur le banc de l\u2019actuel 6e de Serie B italienne.",
        "link": "https://www.20min.ch/fr/548050554913"
    },
    {
        "title": "Cybers\u00e9curit\u00e9: plus de trois mois pour colmater une faille",
        "summary": "Malgr\u00e9 une alerte lanc\u00e9e en juillet, Berne n\u2019a rebouch\u00e9 qu\u2019en novembre un acc\u00e8s \u00e0 la maquette d\u2019un portail destin\u00e9 aux entreprises. Ce laps de temps interpelle.",
        "link": "https://www.20min.ch/fr/543189047687"
    },
    {
        "title": "L\u2019Etna se calme un peu, le DFAE appelle \u00e0 la vigilance",
        "summary": "La forte activit\u00e9 sismique en Sicile et en Islande a incit\u00e9 le DFAE \u00e0 publier un rappel \u00e0 l\u2019ordre. Dans les zones, il faut se plier aux instructions des autorit\u00e9s locales.",
        "link": "https://www.20min.ch/fr/256453605476"
    },
    {
        "title": "Un forcen\u00e9 a \u00e9t\u00e9 interpell\u00e9 \u00e0 son domicile",
        "summary": "Un sexag\u00e9naire a notamment menac\u00e9 d\u2019incendier son logement. La police et les secours ont finalement r\u00e9ussi \u00e0 le ma\u00eetriser. Il n\u2019y a pas eu de bless\u00e9.",
        "link": "https://www.20min.ch/fr/428596498517"
    },
    {
        "title": "Un clip amusant, pour promouvoir une sexualit\u00e9 joyeuse",
        "summary": "L\u2019association Suisse GummiLove a pour objectif que les jeunes apprennent \u00e0 aborder la sexualit\u00e9 de mani\u00e8re s\u00fbre et sans tabou. Pour partager le message, elle vient de publier une vid\u00e9o qui fait sourire.",
        "link": "https://www.20min.ch/fr/462119029665"
    },
    {
        "title": "Apple mise sur son \u00abambitieux\u00bb iOS\u00a018 pour vendre l\u2019iPhone\u00a016",
        "summary": "La firme de Cupertino compte rattraper son retard dans le domaine de l\u2019IA g\u00e9n\u00e9rative en dotant ses prochains smartphones de fonctionnalit\u00e9s exclusives.",
        "link": "https://www.20min.ch/fr/872960908669"
    },
    {
        "title": "Homer ne se privera pas d\u2019\u00e9trangler Bart",
        "summary": "Le p\u00e8re de famille n\u2019a plus serr\u00e9 le cou de son fiston depuis plusieurs saisons. Contrairement \u00e0 ce que l\u2019on peut lire sur la Toile, il pourrait recommencer.",
        "link": "https://www.20min.ch/fr/825632981314"
    },
    {
        "title": "Faute de carburant, les h\u00f4pitaux de Gaza n\u2019ont plus d\u2019\u00e9lectricit\u00e9",
        "summary": "Des m\u00e9decins du nord de la bande de Gaza sont oblig\u00e9s d\u2019op\u00e9rer \u00e0 la bougie, \u00e0 la lampe torche, ou seulement avec les lumi\u00e8res des t\u00e9l\u00e9phones portables et des femmes accouchent dans la rue.",
        "link": "https://www.20min.ch/fr/926203185863"
    },
    {
        "title": "Antis\u00e9mitisme: 330\u00a0enqu\u00eates ouvertes en France depuis le 7\u00a0octobre",
        "summary": "Selon le ministre de l\u2019Int\u00e9rieur, les auteurs des actes antis\u00e9mites recens\u00e9s ces derni\u00e8res semaines sont souvent tr\u00e8s jeunes, voire mineurs.",
        "link": "https://www.20min.ch/fr/514775102302"
    },
    {
        "title": "Zermatt outrepasse encore des nouvelles directives du Canton",
        "summary": "Tandis que la m\u00e9t\u00e9o a enterr\u00e9 tout espoir de course transfrontali\u00e8re, les organisateurs ne respectent toujours pas la loi, qui leur a pourtant \u00e9t\u00e9 pr\u00e9cis\u00e9e le 10 novembre. Du c\u00f4t\u00e9 des autorit\u00e9s, le silence est de mise.",
        "link": "https://www.20min.ch/fr/149031786725"
    },
    {
        "title": "Des arrestations apr\u00e8s la mort de Fayed, 10\u00a0ans, victime collat\u00e9rale \u00e0 N\u00eemes",
        "summary": "L\u2019enfant avait re\u00e7u une balle provenant d\u2019une fusillade entre trafiquants de drogue le 21\u00a0ao\u00fbt. Au moins cinq personnes ont \u00e9t\u00e9 plac\u00e9es en garde \u00e0 vue lundi.",
        "link": "https://www.20min.ch/fr/722305312598"
    },
    {
        "title": "Pierluigi Tami: \u00abNous discuterons avec Yakin en d\u00e9cembre\u00bb",
        "summary": "Le s\u00e9lectionneur de l'\u00e9quipe de Suisse sera-t-il toujours en poste apr\u00e8s l'Euro? Le directeur des \u00e9quipes nationales a d\u00e9taill\u00e9 la position de l'ASF, lundi.",
        "link": "https://www.20min.ch/fr/654881465602"
    },
    {
        "title": "Cinq morts, dont trois enfants, dans un incendie \u00e0 Londres",
        "summary": "Un incendie a d\u00e9truit le rez-de-chauss\u00e9e et le premier \u00e9tage d\u2019une maison de l\u2019ouest de la capitale britannique, dimanche.",
        "link": "https://www.20min.ch/fr/195493945843"
    },
    {
        "title": "Niet aux publicit\u00e9s sexistes dans l\u2019espace public",
        "summary": "Le Canton a accept\u00e9 une motion visant \u00e0 interdire les publicit\u00e9s sexistes dans l\u2019espace public fribourgeois.",
        "link": "https://www.20min.ch/fr/960202837364"
    },
    {
        "title": "\u00c0 15 ans, il envoie la voiture de papa dans le d\u00e9cor",
        "summary": "Dans la nuit de samedi \u00e0 dimanche, un ado a \u00e9t\u00e9 victime d\u2019un accident de voiture \u00e0 Jenins. Heureusement, le mineur a pu sortir sans encombre de la voiture couch\u00e9e sur le flanc.",
        "link": "https://www.20min.ch/fr/367164024576"
    },
    {
        "title": "Renoncer aux compl\u00e9mentaires pour \u00e9conomiser",
        "summary": "Chaque ann\u00e9e, pr\u00e8s de 2% des assur\u00e9s quittent leur compl\u00e9mentaire pour \u00e9viter des co\u00fbts. Pas de quoi mettre en p\u00e9ril l\u2019existence des cliniques priv\u00e9es.",
        "link": "https://www.20min.ch/fr/823621069689"
    },
    {
        "title": "Drifts et exc\u00e8s de vitesse: logements fouill\u00e9s, hommes arr\u00eat\u00e9s",
        "summary": "Trois Suisses et un Polonais ont \u00e9t\u00e9 interpell\u00e9s par les autorit\u00e9s apr\u00e8s une enqu\u00eate. Ils totalisent plus de 20 d\u00e9lits routiers pr\u00e9sum\u00e9s.",
        "link": "https://www.20min.ch/fr/344411394367"
    },
    {
        "title": "Barton Cowperthwaite, star de \u00abTiny Pretty Things\u00bb, a un cancer",
        "summary": "L\u2019acteur de 31 ans a confi\u00e9 sur Instagram qu\u2019il \u00e9tait atteint d\u2019un gliome et qu\u2019il allait devoir subir une intervention au cerveau.",
        "link": "https://www.20min.ch/fr/208510991411"
    },
    {
        "title": "L\u2019\u00e9quipe de Suisse s\u2019est retrouv\u00e9e \u00e0 B\u00e2le",
        "summary": "Les 24 joueurs convoqu\u00e9s par Murat Yakin avaient rendez-vous ce lundi. Ils d\u00e9colleront pour la Hongrie, mardi, en fin de matin\u00e9e.",
        "link": "https://www.20min.ch/fr/909232915375"
    },
    {
        "title": "La gu\u00e9parde Alima s\u2019en est all\u00e9e",
        "summary": "Le zoo de B\u00e2le pleure la mort de sa gu\u00e9parde Alima, euthanasi\u00e9e pour des raisons de sant\u00e9. Une tristesse partag\u00e9e par les internautes sur Facebook.",
        "link": "https://www.20min.ch/fr/346580306012"
    },
    {
        "title": "Ivre, il emprunte l\u2019autoroute dans le mauvais sens",
        "summary": "En pleine nuit pr\u00e8s de Palexpo, la police a interpell\u00e9 un automobiliste qui a roulait \u00e0 contresens sur le contournement de Gen\u00e8ve. Il n\u2019y a pas eu de bless\u00e9.",
        "link": "https://www.20min.ch/fr/703412964164"
    },
    {
        "title": "Des voleurs bloquent un tunnel ferroviaire vers l\u2019Italie",
        "summary": "Deux r\u00f4deurs ont tent\u00e9 de s'introduire dans un magasin en gare de Chiasso. Ils se sont ensuite enfuis en empruntant le tunnel menant \u00e0 C\u00f4me, bloquant ainsi deux trains.",
        "link": "https://www.20min.ch/fr/583801462744"
    },
    {
        "title": "Les Vaudois pourront faire une 12e ann\u00e9e d\u2019\u00e9cole \u00e0 Zurich, \u00e0 l\u2019\u0153il",
        "summary": "Vaud et Zurich vont signer ce mardi un accord permettant \u00e0 leurs \u00e9l\u00e8ves d\u2019effectuer une douzi\u00e8me ann\u00e9e qualifi\u00e9e de \u00ablinguistique\u00bb, dans une \u00e9cole de l\u2019autre canton. En principe, l\u2019\u00e9colage ne sera pas factur\u00e9.",
        "link": "https://www.20min.ch/fr/155574646404"
    },
    {
        "title": "Une demande de visa Schengen passera bient\u00f4t par Internet",
        "summary": "Les personnes en qu\u00eate d\u2019un visa Schengen pourront faire leur demande en passant par une plateforme europ\u00e9enne. La date d\u2019entr\u00e9e en vigueur n\u2019est pas encore fix\u00e9e.",
        "link": "https://www.20min.ch/fr/539856429477"
    },
    {
        "title": "Faut-il faire remarquer \u00e0 quelqu\u2019un qu\u2019il sent mauvais?",
        "summary": "Quand une personne sent mauvais, c\u2019est avant tout son entourage qui en p\u00e2tit. Voici comment aborder des sujets tels que les odeurs corporelles ou les crottes de nez.",
        "link": "https://www.20min.ch/fr/869640966003"
    }
]